doxypypy/__init__.py
doxypypy/doxypypy.py
doxypypy/test/__init__.py
doxypypy/test/sample_async.out.py
doxypypy/test/sample_async.outbare.py
doxypypy/test/sample_async.outnc.py
doxypypy/test/sample_async.outnn.py
doxypypy/test/sample_async.py
doxypypy/test/sample_docexample.out.py
doxypypy/test/sample_docexample.outbare.py
doxypypy/test/sample_docexample.outnc.py
doxypypy/test/sample_docexample.outnn.py
doxypypy/test/sample_docexample.py
doxypypy/test/sample_google.out.py
doxypypy/test/sample_google.outbare.py
doxypypy/test/sample_google.outnc.py
doxypypy/test/sample_google.outnn.py
doxypypy/test/sample_google.py
doxypypy/test/sample_interfaces.out.py
doxypypy/test/sample_interfaces.outbare.py
doxypypy/test/sample_interfaces.outnc.py
doxypypy/test/sample_interfaces.outnn.py
doxypypy/test/sample_interfaces.py
doxypypy/test/sample_maze.out.py
doxypypy/test/sample_maze.outbare.py
doxypypy/test/sample_maze.outnc.py
doxypypy/test/sample_maze.outnn.py
doxypypy/test/sample_maze.py
doxypypy/test/sample_pep.out.py
doxypypy/test/sample_pep.outbare.py
doxypypy/test/sample_pep.outnc.py
doxypypy/test/sample_pep.outnn.py
doxypypy/test/sample_pep.py
doxypypy/test/sample_privacy.out.py
doxypypy/test/sample_privacy.outbare.py
doxypypy/test/sample_privacy.outnc.py
doxypypy/test/sample_privacy.outnn.py
doxypypy/test/sample_privacy.py
doxypypy/test/sample_rawdocstring.out.py
doxypypy/test/sample_rawdocstring.outbare.py
doxypypy/test/sample_rawdocstring.outnc.py
doxypypy/test/sample_rawdocstring.outnn.py
doxypypy/test/sample_rawdocstring.py
doxypypy/test/sample_rstexample.out.py
doxypypy/test/sample_rstexample.outbare.py
doxypypy/test/sample_rstexample.outeq.py
doxypypy/test/sample_rstexample.outnc.py
doxypypy/test/sample_rstexample.outnn.py
doxypypy/test/sample_rstexample.py
doxypypy/test/sample_sections.out.py
doxypypy/test/sample_sections.outbare.py
doxypypy/test/sample_sections.outnc.py
doxypypy/test/sample_sections.outnn.py
doxypypy/test/sample_sections.py
doxypypy-0.8.8.7.dist-info/LICENSE.txt
doxypypy-0.8.8.7.dist-info/METADATA
doxypypy-0.8.8.7.dist-info/WHEEL
doxypypy-0.8.8.7.dist-info/entry_points.txt
doxypypy-0.8.8.7.dist-info/top_level.txt
doxypypy-0.8.8.7.dist-info/RECORD
