Metadata-Version: 2.1
Name: doxypypy
Version: 0.8.8.7
Summary: A Doxygen filter for Python
Home-page: https://github.com/Feneric/doxypypy
Author: Eric W. Brown
Keywords: Doxygen filter Python documentation
Classifier: Development Status :: 4 - Beta
Classifier: Environment :: Console
Classifier: Environment :: Plugins
Classifier: Intended Audience :: Developers
Classifier: Intended Audience :: System Administrators
Classifier: License :: OSI Approved :: GNU General Public License v2 (GPLv2)
Classifier: Natural Language :: English
Classifier: Operating System :: MacOS :: MacOS X
Classifier: Operating System :: POSIX
Classifier: Operating System :: Unix
Classifier: Programming Language :: Python
Classifier: Topic :: Software Development :: Documentation
License-File: LICENSE.txt
Requires-Dist: chardet
Provides-Extra: testing
Requires-Dist: pytest ; extra == 'testing'
Requires-Dist: tox ; extra == 'testing'
